odoo/addons/attachment_unindex_content/README.rst
odoo/addons/attachment_unindex_content/__init__.py
odoo/addons/attachment_unindex_content/__manifest__.py
odoo/addons/attachment_unindex_content/hooks.py
odoo/addons/attachment_unindex_content/i18n/attachment_unindex_content.pot
odoo/addons/attachment_unindex_content/i18n/ca.po
odoo/addons/attachment_unindex_content/i18n/es.po
odoo/addons/attachment_unindex_content/i18n/es_AR.po
odoo/addons/attachment_unindex_content/i18n/it.po
odoo/addons/attachment_unindex_content/models/__init__.py
odoo/addons/attachment_unindex_content/models/ir_attachment.py
odoo/addons/attachment_unindex_content/readme/CONTRIBUTORS.md
odoo/addons/attachment_unindex_content/readme/CREDITS.md
odoo/addons/attachment_unindex_content/readme/DESCRIPTION.md
odoo/addons/attachment_unindex_content/static/description/icon.png
odoo/addons/attachment_unindex_content/static/description/index.html
odoo_addon_attachment_unindex_content-18.0.1.0.0.2.dist-info/METADATA
odoo_addon_attachment_unindex_content-18.0.1.0.0.2.dist-info/WHEEL
odoo_addon_attachment_unindex_content-18.0.1.0.0.2.dist-info/top_level.txt
odoo_addon_attachment_unindex_content-18.0.1.0.0.2.dist-info/RECORD
